zsp_be_py/__build_num__.py
zsp_be_py/actor.py
zsp_be_py/impl/__init__.py
zsp_be_py/impl/deferred_task_caller.py
zsp_be_py/impl/env_config.py
zsp_be_py/impl/env_config_cocotb.py
zsp_be_py/impl/function_impl_trap.py
zsp_be_py/impl/runner.py
zsp_be_py/impl/runner_backend.py
zsp_be_py/impl/runner_backend_async_io.py
zsp_be_py/impl/runner_backend_cocotb.py
zsp_be_py/impl/runner_thread.py
zsp_be_py/impl/task_build_param_xformer.py
zsp_be_py/impl/task_build_task_caller.py
zsp_be_py/impl/task_caller.py
zuspec_be_py-0.0.1.8427800336.dist-info/LICENSE
zuspec_be_py-0.0.1.8427800336.dist-info/METADATA
zuspec_be_py-0.0.1.8427800336.dist-info/WHEEL
zuspec_be_py-0.0.1.8427800336.dist-info/top_level.txt
zuspec_be_py-0.0.1.8427800336.dist-info/RECORD
