Metadata-Version: 2.1
Name: zuspec-be-py
Version: 0.0.1.8427800336
Summary: Co-specification of hardware, software, design, and test behavior
Home-page: https://github.com/zuspec/zuspec-be-py
Author: Matthew Ballance
Author-email: matt.ballance@gmail.com
License: Apache 2.0
Keywords: PSS,Functional Verification,RTL,Verilog,SystemVerilog
License-File: LICENSE
Requires-Dist: zuspec-arl-dm
Requires-Dist: zuspec-arl-eval
Requires-Dist: zuspec-fe-parser
Requires-Dist: zuspec-parser
